{"version": 0.6, "generator": "Overpass API 0.7.62.5 1bd436f1", "osm3s": {"timestamp_osm_base": "2025-05-24T17:52:15Z", "copyright": "The data included in this document is from www.openstreetmap.org. The data is made available under ODbL."}, "elements": [{"type": "node", "id": 198490752, "lat": 16.3580559, "lon": 120.8871609, "tags": {"admin_level": "6", "admin_type:PH": "municipality", "name": "Kayapa", "place": "town", "population": "26469", "population:date": "2020-05-01", "ref": "025010000", "source:population": "Philippine Statistics Authority", "wikidata": "Q51486", "wikimedia_commons": "Category:Kayapa", "wikipedia": "en:Kayapa"}}, {"type": "node", "id": 198492701, "lat": 16.1590291, "lon": 120.9381714, "tags": {"admin_level": "6", "designation": "municipality", "name": "Santa Fe", "place": "town", "population": "18276", "population:date": "2020-05-01", "ref": "025012000", "source:population": "Philippine Statistics Authority", "website": "https://santafe-nvizcaya.gov.ph/", "wikidata": "Q51493", "wikimedia_commons": "Category:Santa Fe, Nueva Vizcaya", "wikipedia": "en:Santa Fe, Nueva Vizcaya"}}, {"type": "node", "id": 198497008, "lat": 16.2842827, "lon": 121.091306, "tags": {"admin_level": "6", "designation": "municipality", "name": "Dupax del Sur", "place": "town", "population": "21224", "population:date": "2020-05-01", "ref": "025008000", "source:population": "Philippine Statistics Authority", "wikidata": "Q51484", "wikimedia_commons": "Category:Dupax del Sur", "wikipedia": "en:Dupax del Sur"}}, {"type": "node", "id": 198502631, "lat": 16.3850624, "lon": 121.1054715, "tags": {"admin_level": "6", "admin_type:PH": "municipality", "gns_classification": "ADM2", "name": "Bambang", "place": "town", "population": "55789", "population:date": "2020-05-01", "postal_code": "3702", "ref": "025004000", "source:population": "Philippine Statistics Authority", "wikidata": "Q51479", "wikimedia_commons": "Category:Bambang, Nueva Vizcaya", "wikipedia": "en:Bambang, Nueva Vizcaya"}}, {"type": "node", "id": 198513809, "lat": 16.2968923, "lon": 121.0340711, "tags": {"admin_level": "6", "designation": "municipality", "name": "Aritao", "place": "town", "population": "42197", "population:date": "2020-05-01", "ref": "025002000", "source:population": "Philippine Statistics Authority", "website": "http://aritao.gov.ph/", "wikidata": "Q51477", "wikimedia_commons": "Category:Aritao", "wikipedia": "en:Aritao"}}, {"type": "node", "id": 1133996431, "lat": 16.0154335, "lon": 121.216052, "tags": {"name": "Abaca", "place": "village"}}, {"type": "node", "id": 1133996434, "lat": 16.0173724, "lon": 121.2636669, "tags": {"name": "Lipuga", "place": "village"}}, {"type": "node", "id": 2170353832, "lat": 16.3043055, "lon": 121.1443519, "tags": {"name": "Mungguia", "place": "village"}}, {"type": "node", "id": 2170431050, "lat": 16.2831671, "lon": 121.1769148, "tags": {"name": "Bitnong", "place": "village"}}, {"type": "node", "id": 2170446831, "lat": 16.3177797, "lon": 121.2941105, "tags": {"admin_level": "6", "designation": "municipality", "name": "Kasibu", "place": "town", "population": "41776", "population:date": "2020-05-01", "ref": "025009000", "source:population": "Philippine Statistics Authority", "wikidata": "Q51485", "wikimedia_commons": "Category:Kasibu", "wikipedia": "en:Kasibu"}}, {"type": "node", "id": 2170703479, "lat": 16.3052934, "lon": 121.1235575, "tags": {"admin_level": "10", "admin_type:PH": "barangay", "name": "Inaban", "place": "village"}}, {"type": "node", "id": 3192508661, "lat": 16.1415164, "lon": 120.9361665, "tags": {"name": "Tactac", "place": "village"}}, {"type": "node", "id": 3192508696, "lat": 16.164189, "lon": 120.8912333, "tags": {"name": "Malliit", "place": "hamlet"}}, {"type": "node", "id": 3192508697, "lat": 16.1714922, "lon": 120.8948165, "tags": {"name": "Pakalbo", "place": "hamlet"}}, {"type": "node", "id": 3192510681, "lat": 16.1546575, "lon": 120.929525, "tags": {"admin_level": "10", "designation": "barangay", "is_in:town": "Santa Fe", "name": "Baracbac", "place": "village"}}, {"type": "node", "id": 3192513064, "lat": 16.1564202, "lon": 120.9042802, "tags": {"admin_level": "10", "designation": "barangay", "is_in:town": "Santa Fe", "name": "Imugan", "place": "village"}}, {"type": "node", "id": 3192513070, "lat": 16.174704, "lon": 120.875478, "tags": {"admin_level": "10", "is_in:province": "Nueva Vizcaya", "is_in:town": "Santa Fe", "name": "Malico", "note": "ongoing boundary dispute", "place": "village", "place:PH": "barangay"}}, {"type": "node", "id": 3192523709, "lat": 16.0739253, "lon": 120.9423396, "tags": {"admin_level": "10", "admin_type:PH": "barangay", "designation": "barangay", "name": "Minuli", "place": "village", "postal_code": "3123"}}, {"type": "node", "id": 3192524579, "lat": 16.0509616, "lon": 120.9539906, "tags": {"admin_level": "10", "admin_type:PH": "barangay", "name": "Putlan", "place": "village"}}, {"type": "node", "id": 3485858800, "lat": 16.3959175, "lon": 120.8860424, "tags": {"admin_level": "11", "admin_type:PH": "sitio", "is_in:village": "Pangawan", "name": "Dayap", "place": "hamlet"}}, {"type": "node", "id": 3719863648, "lat": 16.3298812, "lon": 121.1248675, "tags": {"name": "CSAP Core Shelter Village - Mabasa", "place": "neighbourhood"}}, {"type": "node", "id": 3719863651, "lat": 16.3048146, "lon": 121.0945761, "tags": {"name": "Gawad Kalinga - Malasin", "place": "neighbourhood"}}, {"type": "node", "id": 3719865952, "lat": 16.3106788, "lon": 121.1693185, "tags": {"admin_level": "10", "designation": "barangay", "name": "Parai", "place": "village"}}, {"type": "node", "id": 3719880981, "lat": 16.2308056, "lon": 121.2125003, "tags": {"admin_level": "10", "designation": "barangay", "is_in:town": "Dupax del Norte", "name": "Oyao", "place": "village", "postal_code": "3706"}}, {"type": "node", "id": 3719880982, "lat": 16.220425, "lon": 121.2205965, "tags": {"FIXME": "outline"}}, {"type": "node", "id": 3719880983, "lat": 16.2132988, "lon": 121.2317552, "tags": {"admin_level": "10", "designation": "barangay", "is_in:town": "Dupax del Norte", "name": "Macabenga", "place": "village", "postal_code": "3706"}}, {"type": "node", "id": 3719886101, "lat": 16.1878958, "lon": 121.254639, "tags": {"admin_level": "10", "admin_type:PH": "barangay", "is_in:town": "Dupax del Norte", "name": "Binuangan", "place": "village", "postal_code": "3706"}}, {"type": "node", "id": 3719888335, "lat": 16.1898952, "lon": 121.2480136, "tags": {"name": "Teggep", "place": "neighbourhood"}}, {"type": "node", "id": 3719902615, "lat": 16.1963862, "lon": 121.2390263, "tags": {"admin_level": "10", "designation": "barangay", "is_in:town": "Dupax del Norte", "name": "Belance", "place": "village", "postal_code": "3706"}}, {"type": "node", "id": 3719913569, "lat": 16.3344646, "lon": 121.1082646, "tags": {"admin_level": "10", "admin_type:PH": "barangay", "name": "Lamo", "place": "village"}}, {"type": "node", "id": 3719934467, "lat": 16.1210871, "lon": 121.3037919, "tags": {"admin_level": "10", "designation": "barangay", "is_in:town": "Dupax del Norte", "name": "Giyan", "place": "village", "postal_code": "3706"}}, {"type": "node", "id": 3719940578, "lat": 16.1626547, "lon": 121.3222263, "tags": {"admin_level": "10", "admin_type:PH": "barangay", "is_in:town": "Dupax del Norte", "name": "Yabbi", "place": "village", "postal_code": "3706"}}, {"type": "node", "id": 3720930912, "lat": 16.220547, "lon": 121.2210484}, {"type": "node", "id": 3720930913, "lat": 16.2205509, "lon": 121.2215164}, {"type": "node", "id": 3720933127, "lat": 16.2207136, "lon": 121.2205078}, {"type": "node", "id": 3720933157, "lat": 16.2209228, "lon": 121.2216616}, {"type": "node", "id": 3720933171, "lat": 16.2210506, "lon": 121.2215244}, {"type": "node", "id": 3720933174, "lat": 16.2210623, "lon": 121.220419}, {"type": "node", "id": 3720933186, "lat": 16.2211804, "lon": 121.2212501}, {"type": "node", "id": 3720933200, "lat": 16.2213141, "lon": 121.220419}, {"type": "node", "id": 3720933212, "lat": 16.2214477, "lon": 121.2209879}, {"type": "node", "id": 3720933217, "lat": 16.2215949, "lon": 121.2206792}, {"type": "node", "id": 3721266413, "lat": 16.3085442, "lon": 121.0391725, "tags": {"name": "Aritao GK Village", "place": "neighbourhood", "short_name": "GK Village"}}, {"type": "node", "id": 3721300966, "lat": 16.1667784, "lon": 121.1795877, "tags": {"name": "Ganao", "place": "village"}}, {"type": "node", "id": 3721318003, "lat": 16.2818478, "lon": 121.2389663, "tags": {"name": "Muta", "place": "village"}}, {"type": "node", "id": 3730496872, "lat": 16.3073041, "lon": 121.1017442, "tags": {"admin_level": "6", "designation": "municipality", "name": "Dupax del Norte", "place": "town", "population": "33295", "population:date": "2020-05-01", "ref": "025007000", "source:population": "Philippine Statistics Authority", "website": "https://dupaxdelnorte.gov.ph/", "wikidata": "Q51483", "wikimedia_commons": "Category:Dupax del Norte", "wikipedia": "en:Dupax del Norte"}}, {"type": "node", "id": 3730496873, "lat": 16.3168681, "lon": 121.0917844, "tags": {"admin_level": "10", "designation": "barangay", "is_in:town": "Dupax del Norte", "name": "Ineangan", "place": "village"}}, {"type": "node", "id": 3884265208, "lat": 16.3785869, "lon": 121.1054584, "tags": {"name": "Juel Homes Subdivision", "place": "neighbourhood"}}, {"type": "node", "id": 3884266124, "lat": 16.3246124, "lon": 121.0704445, "tags": {"name": "Gabut", "place": "village"}}, {"type": "node", "id": 3884266130, "lat": 16.3118481, "lon": 121.0488805, "tags": {"admin_level": "10", "name": "Darapidap", "place": "village", "place:PH": "barangay"}}, {"type": "node", "id": 4418183836, "lat": 16.3107445, "lon": 120.9472453, "tags": {"admin_level": "10", "admin_type:PH": "barangay", "alt_name": "Pinkian", "name": "Pingkian", "place": "village"}}, {"type": "node", "id": 4418183837, "lat": 16.3444866, "lon": 120.9249661, "tags": {"admin_level": "10", "admin_type:PH": "barangay", "name": "Tidang Village", "place": "village"}}, {"type": "node", "id": 4418183838, "lat": 16.355371, "lon": 120.8931684, "tags": {"admin_level": "10", "admin_type:PH": "barangay", "name": "Castillo Village", "place": "village"}}, {"type": "node", "id": 4418183839, "lat": 16.3800278, "lon": 120.8708855, "tags": {"admin_level": "10", "admin_type:PH": "barangay", "name": "Pangawan", "place": "village"}}, {"type": "node", "id": 4418183840, "lat": 16.3147713, "lon": 120.9728443, "tags": {"admin_level": "10", "admin_type:PH": "barangay", "is_in:town": "Aritao", "name": "Baan", "place": "village"}}, {"type": "node", "id": 4418183841, "lat": 16.3592538, "lon": 121.0092419, "tags": {"name": "San Fabian", "place": "village"}}, {"type": "node", "id": 4418207146, "lat": 16.3724403, "lon": 121.0212677, "tags": {"name": "Salinas", "place": "village"}}, {"type": "node", "id": 4418207917, "lat": 16.3766355, "lon": 121.0539007, "tags": {"name": "Barat", "place": "village"}}, {"type": "node", "id": 4418267175, "lat": 16.3885037, "lon": 121.0873772, "tags": {"name": "San Leonardo", "place": "village"}}, {"type": "node", "id": 4418267179, "lat": 16.3503683, "lon": 121.0937373, "tags": {"name": "Almaguer South", "place": "village"}}, {"type": "node", "id": 4418722317, "lat": 16.2986892, "lon": 121.0006333, "tags": {"admin_level": "10", "admin_type:PH": "barangay", "name": "Kirang", "place": "village"}}, {"type": "node", "id": 4422215007, "lat": 16.4106353, "lon": 120.963217, "tags": {"admin_level": "10", "designation": "barangay", "name": "Babadi", "place": "village"}}, {"type": "node", "id": 4422215083, "lat": 16.3413646, "lon": 120.8930558, "tags": {"admin_level": "10", "admin_type:PH": "barangay", "name": "Besong", "place": "village"}}, {"type": "node", "id": 4431014402, "lat": 16.3021708, "lon": 121.0600623, "tags": {"name": "Tucanon", "place": "village"}}, {"type": "node", "id": 4431014403, "lat": 16.3119952, "lon": 121.0717005, "tags": {"name": "Mangayang", "place": "village"}}, {"type": "node", "id": 4431014404, "lat": 16.2999042, "lon": 121.0781223, "tags": {"name": "Sta. Maria", "place": "village"}}, {"type": "node", "id": 4431014405, "lat": 16.2907803, "lon": 121.0857827, "tags": {"name": "Domang", "place": "village"}}, {"type": "node", "id": 4431014406, "lat": 16.2821091, "lon": 121.095267, "tags": {"name": "Dopaj", "place": "village"}}, {"type": "node", "id": 4432215412, "lat": 16.2631903, "lon": 121.1048689, "tags": {"name": "Palabotan", "place": "village"}}, {"type": "node", "id": 4432215413, "lat": 16.2287369, "lon": 121.1338683, "tags": {"admin_level": "10", "is_in:town": "Dupax del Sur", "name": "Carolotan", "place": "village", "place:PH": "barangay"}}, {"type": "node", "id": 4432215557, "lat": 16.2061686, "lon": 121.1542196, "tags": {"name": "Kinabuan", "place": "village"}}, {"type": "node", "id": 4691650649, "lat": 16.2699565, "lon": 121.2558935, "tags": {"name": "Bulala", "place": "village"}}, {"type": "node", "id": 4691660089, "lat": 16.3246837, "lon": 121.122249, "tags": {"admin_level": "10", "admin_type:PH": "barangay", "name": "Mabasa", "place": "village"}}, {"type": "node", "id": 5243386783, "lat": 16.3179174, "lon": 121.2920218, "tags": {"name": "Kasibu Poblacion", "place": "village"}}, {"type": "node", "id": 5243386784, "lat": 16.3316925, "lon": 121.3100461, "tags": {"name": "Pudi", "place": "village"}}, {"type": "node", "id": 5243386785, "lat": 16.297387, "lon": 121.3007652, "tags": {"name": "Seguem", "place": "village"}}, {"type": "node", "id": 5243386787, "lat": 16.3298344, "lon": 121.2795623, "tags": {"name": "Watwat", "place": "village"}}, {"type": "node", "id": 5243386788, "lat": 16.3361305, "lon": 121.2510447, "tags": {"admin_level": "10", "is_in:town": "Kasibu", "name": "Kongkong", "place": "village", "place:PH": "barangay"}}, {"type": "node", "id": 5243386789, "lat": 16.3450195, "lon": 121.2377786, "tags": {"name": "Makalong", "place": "village"}}, {"type": "node", "id": 5645280328, "lat": 16.3245897, "lon": 121.104375, "tags": {"name": "CSAP Core Shelter Village - Lamo", "place": "neighbourhood"}}, {"type": "node", "id": 5645289298, "lat": 16.3104405, "lon": 121.1669926, "tags": {"name": "Gawad Kalinga Parai", "place": "neighbourhood"}}, {"type": "node", "id": 7296390094, "lat": 16.1557508, "lon": 121.0531005, "tags": {"name": "Canabuan", "place": "village"}}, {"type": "node", "id": 8176904513, "lat": 16.1087719, "lon": 121.0692608, "tags": {"place": "hamlet"}}, {"type": "node", "id": 8176923072, "lat": 16.0900576, "lon": 121.0443109, "tags": {"place": "hamlet"}}, {"type": "node", "id": 8176923329, "lat": 16.1503019, "lon": 121.0295534, "tags": {"place": "hamlet"}}, {"type": "node", "id": 8176923436, "lat": 16.145077, "lon": 121.0224724, "tags": {"place": "hamlet"}}, {"type": "node", "id": 8176924602, "lat": 16.0164924, "lon": 121.2270927, "tags": {"place": "hamlet"}}, {"type": "node", "id": 8176924603, "lat": 16.0237754, "lon": 121.2127054, "tags": {"admin_level": "10", "designation": "barangay", "name": "Talbec", "place": "village"}}, {"type": "node", "id": 8176924604, "lat": 15.9975889, "lon": 121.1987793, "tags": {"place": "hamlet"}}, {"type": "node", "id": 8178887252, "lat": 16.1903242, "lon": 121.2970018, "tags": {"admin_level": "10", "admin_type:PH": "barangay", "is_in:town": "Nagtipunan", "name": "Mataddi", "place": "village"}}, {"type": "node", "id": 8178890197, "lat": 16.3044727, "lon": 121.2905377, "tags": {"place": "hamlet"}}, {"type": "node", "id": 8178890331, "lat": 16.2795463, "lon": 121.3154554, "tags": {"admin_level": "10", "designation": "barangay", "name": "Siguem", "place": "village"}}, {"type": "node", "id": 8178890355, "lat": 16.2679394, "lon": 121.2936598, "tags": {"place": "village"}}, {"type": "node", "id": 8201695523, "lat": 16.2026131, "lon": 121.0054243, "tags": {"place": "hamlet"}}, {"type": "node", "id": 8201700528, "lat": 16.2136135, "lon": 121.0028011, "tags": {"place": "hamlet"}}, {"type": "node", "id": 8201700529, "lat": 16.2349944, "lon": 121.0046679, "tags": {"place": "hamlet"}}, {"type": "node", "id": 8201700530, "lat": 16.2405311, "lon": 120.9919596, "tags": {"admin_level": "10", "admin_type:PH": "barangay", "name": "Bone South", "place": "village"}}, {"type": "node", "id": 8201700531, "lat": 16.2605341, "lon": 121.0123229, "tags": {"admin_level": "10", "admin_type:PH": "barangay", "name": "Bone North", "place": "village"}}, {"type": "node", "id": 8201700532, "lat": 16.2318268, "lon": 121.0536128, "tags": {"place": "village"}}, {"type": "node", "id": 8201700706, "lat": 16.228994, "lon": 120.9756517, "tags": {"admin_level": "10", "admin_type:PH": "barangay", "name": "Calitlitan", "place": "village"}}, {"type": "node", "id": 8201701407, "lat": 16.1730859, "lon": 121.1921865, "tags": {"place": "hamlet"}}, {"type": "node", "id": 8201701408, "lat": 16.1908239, "lon": 121.2044871, "tags": {"place": "hamlet"}}, {"type": "node", "id": 8201701481, "lat": 16.1500391, "lon": 121.2445056, "tags": {"place": "hamlet"}}, {"type": "node", "id": 8201701482, "lat": 16.1245831, "lon": 121.2145185, "tags": {"place": "hamlet"}}, {"type": "node", "id": 8201701483, "lat": 16.1454119, "lon": 121.2239331, "tags": {"place": "hamlet"}}, {"type": "node", "id": 8201701484, "lat": 16.1631936, "lon": 121.1599034, "tags": {"place": "hamlet"}}, {"type": "node", "id": 8201701485, "lat": 16.1464374, "lon": 121.1582512, "tags": {"admin_level": "10", "designation": "barangay", "name": "Sanguit", "place": "village"}}, {"type": "node", "id": 8201701486, "lat": 16.0957426, "lon": 121.1970681, "tags": {"place": "hamlet"}}, {"type": "node", "id": 8201701577, "lat": 16.1950791, "lon": 121.0727906, "tags": {"admin_level": "10", "admin_type:PH": "barangay", "name": "Anayo", "place": "village"}}, {"type": "node", "id": 8201701730, "lat": 16.1927094, "lon": 121.0630917, "tags": {"admin_level": "10", "name": "Santa Clara", "place": "village", "place:PH": "barangay"}}, {"type": "node", "id": 8201701731, "lat": 16.1851982, "lon": 121.0590631, "tags": {"place": "village"}}, {"type": "node", "id": 8201701732, "lat": 16.2031411, "lon": 120.9466892, "tags": {"admin_level": "10", "admin_type:PH": "barangay", "is_in:town": "Santa Fe", "name": "Bacneng", "place": "village"}}, {"type": "node", "id": 8201701987, "lat": 16.1727768, "lon": 120.9639358, "tags": {"admin_level": "10", "admin_type:PH": "barangay", "name": "Sinapaoan", "place": "village"}}, {"type": "node", "id": 8201702082, "lat": 16.1900923, "lon": 120.9474134, "tags": {"admin_level": "10", "admin_type:PH": "barangay", "is_in:town": "Santa Fe", "name": "Baliling", "place": "village"}}, {"type": "node", "id": 8201702086, "lat": 16.1891444, "lon": 120.9320497, "tags": {"place": "hamlet"}}, {"type": "node", "id": 8201702293, "lat": 16.1689178, "lon": 120.952118, "tags": {"place": "hamlet"}}, {"type": "node", "id": 8201702294, "lat": 16.1588913, "lon": 120.9428912, "tags": {"admin_level": "10", "designation": "barangay", "is_in:town": "Santa Fe", "name": "Villaflores", "place": "village"}}, {"type": "node", "id": 8201702295, "lat": 16.1866948, "lon": 120.8959874, "tags": {"place": "hamlet"}}, {"type": "node", "id": 8201702430, "lat": 16.0938098, "lon": 120.9287775, "tags": {"admin_level": "10", "name": "Capintalan", "place": "village", "place:PH": "barangay"}}, {"type": "node", "id": 8215135901, "lat": 16.2954211, "lon": 121.3091683, "tags": {"admin_level": "10", "designation": "barangay", "name": "Pudi", "place": "village"}}, {"type": "node", "id": 8215135902, "lat": 16.2905965, "lon": 121.3196504, "tags": {"place": "hamlet"}}, {"type": "node", "id": 8215135903, "lat": 16.3370585, "lon": 121.2815228, "tags": {"place": "hamlet"}}, {"type": "node", "id": 8215136285, "lat": 16.3108878, "lon": 121.3085943, "tags": {"place": "hamlet"}}, {"type": "node", "id": 8215136584, "lat": 16.3526069, "lon": 121.249339, "tags": {"admin_level": "10", "designation": "barangay", "name": "Cordon", "place": "village"}}, {"type": "node", "id": 8215136585, "lat": 16.3572704, "lon": 121.2287772, "tags": {"place": "hamlet"}}, {"type": "node", "id": 8215136830, "lat": 16.3181677, "lon": 121.2500256, "tags": {"place": "hamlet"}}, {"type": "node", "id": 8215136972, "lat": 16.3294319, "lon": 121.292029, "tags": {"admin_level": "10", "designation": "barangay", "name": "Alloy", "place": "village"}}, {"type": "node", "id": 8215136973, "lat": 16.3063133, "lon": 121.2289944, "tags": {"place": "hamlet"}}, {"type": "node", "id": 8215137239, "lat": 16.2914049, "lon": 121.2680447, "tags": {"admin_level": "10", "designation": "barangay", "name": "Lupa", "place": "village"}}, {"type": "node", "id": 8215137245, "lat": 16.2722238, "lon": 121.2313199, "tags": {"place": "hamlet"}}, {"type": "node", "id": 8215137319, "lat": 16.2648805, "lon": 121.1890483, "tags": {"admin_level": "11", "designation": "purok", "is_in:village": "Bitnong", "name": "Naruron", "place": "hamlet"}}, {"type": "node", "id": 8215137320, "lat": 16.2449912, "lon": 121.201821, "tags": {"place": "hamlet"}}, {"type": "node", "id": 8215137321, "lat": 16.2542769, "lon": 121.1874604, "tags": {"place": "hamlet"}}, {"type": "node", "id": 8215137875, "lat": 16.2515319, "lon": 121.1389607, "tags": {"place": "hamlet"}}, {"type": "node", "id": 8215137876, "lat": 16.2357824, "lon": 121.1564648, "tags": {"place": "hamlet"}}, {"type": "node", "id": 8215137877, "lat": 16.2218086, "lon": 121.1682987, "tags": {"place": "hamlet"}}, {"type": "node", "id": 8215138050, "lat": 16.2276239, "lon": 121.1742103, "tags": {"place": "hamlet"}}, {"type": "node", "id": 8215138708, "lat": 16.2541482, "lon": 121.1052561, "tags": {"place": "hamlet"}}, {"type": "node", "id": 8215138763, "lat": 16.208483, "lon": 121.0976922, "tags": {"admin_level": "10", "designation": "barangay", "name": "Banila", "place": "village"}}, {"type": "node", "id": 8215138795, "lat": 16.3152485, "lon": 121.1488742, "tags": {"place": "hamlet"}}, {"type": "node", "id": 8215138796, "lat": 16.3163143, "lon": 121.1744624, "tags": {"place": "hamlet"}}, {"type": "node", "id": 8215139071, "lat": 16.3155677, "lon": 121.1953139, "tags": {"admin_level": "11", "designation": "sitio", "name": "Domang", "place": "hamlet"}}, {"type": "node", "id": 8215139220, "lat": 16.3016151, "lon": 121.1987042, "tags": {"place": "hamlet"}}, {"type": "node", "id": 8215139221, "lat": 16.2980573, "lon": 121.1898208, "tags": {"place": "hamlet"}}, {"type": "node", "id": 8215139603, "lat": 16.2842785, "lon": 121.0556298, "tags": {"admin_level": "10", "admin_type:PH": "barangay", "name": "Tucanon", "place": "village"}}, {"type": "node", "id": 8215139604, "lat": 16.2733619, "lon": 121.0548681, "tags": {"admin_level": "10", "admin_type:PH": "barangay", "name": "Tabueng", "place": "village"}}, {"type": "node", "id": 8215139605, "lat": 16.265313, "lon": 121.0414517, "tags": {"admin_level": "10", "admin_type:PH": "barangay", "name": "Comon", "place": "village"}}, {"type": "node", "id": 8215139606, "lat": 16.2785319, "lon": 121.006245, "tags": {"place": "village"}}, {"type": "node", "id": 8215139607, "lat": 16.2832126, "lon": 120.9719717, "tags": {"place": "hamlet"}}, {"type": "node", "id": 8215139716, "lat": 16.3003743, "lon": 120.887171, "tags": {"place": "village"}}, {"type": "node", "id": 8215139736, "lat": 16.2496522, "lon": 120.8837405, "tags": {"admin_type:PH": "sitio", "is_in:town": "Kayapa", "is_in:village": "Cabalatan-Alang", "name": "Ban-et", "place": "hamlet", "source:population": "Philippine Statistics Authority"}}, {"type": "node", "id": 8215140272, "lat": 16.3548151, "lon": 121.0546803, "tags": {"admin_level": "10", "designation": "barangay", "name": "Mauan", "place": "village"}}, {"type": "node", "id": 8215140418, "lat": 16.3426773, "lon": 120.9863377, "tags": {"name": "Paltog West", "place": "hamlet"}}, {"type": "node", "id": 8215140437, "lat": 16.3212927, "lon": 120.9361803, "tags": {"place": "hamlet"}}, {"type": "node", "id": 8215140438, "lat": 16.3393776, "lon": 120.8797359, "tags": {"place": "hamlet"}}, {"type": "node", "id": 8215140442, "lat": 16.2828676, "lon": 120.8691949, "tags": {"name": "Alupat", "place": "hamlet"}}, {"type": "node", "id": 8220555159, "lat": 16.4172785, "lon": 121.3240868, "tags": {"place": "village"}}, {"type": "node", "id": 8220557034, "lat": 16.3656011, "lon": 121.2271088, "tags": {"place": "hamlet"}}, {"type": "node", "id": 8220557035, "lat": 16.3675235, "lon": 121.2438539, "tags": {"place": "hamlet"}}, {"type": "node", "id": 8220557075, "lat": 16.3718392, "lon": 121.2568465, "tags": {"place": "hamlet"}}, {"type": "node", "id": 8220557095, "lat": 16.3864688, "lon": 121.2485558, "tags": {"place": "hamlet"}}, {"type": "node", "id": 8220557154, "lat": 16.3872768, "lon": 121.2440363, "tags": {"place": "hamlet"}}, {"type": "node", "id": 8220557574, "lat": 16.3893405, "lon": 121.2621921, "tags": {"place": "hamlet"}}, {"type": "node", "id": 8220558474, "lat": 16.3781107, "lon": 121.2302577, "tags": {"place": "hamlet"}}, {"type": "node", "id": 8220558475, "lat": 16.3885248, "lon": 121.2151274, "tags": {"place": "hamlet"}}, {"type": "node", "id": 8220558476, "lat": 16.3950941, "lon": 121.2135369, "tags": {"admin_level": "10", "designation": "barangay", "name": "Antutot", "place": "village"}}, {"type": "node", "id": 8220558477, "lat": 16.3804164, "lon": 121.178593, "tags": {"place": "hamlet"}}, {"type": "node", "id": 8220558478, "lat": 16.3691551, "lon": 121.1358923, "tags": {"admin_level": "11", "designation": "sitio", "name": "Santo Ni\u00f1o", "place": "hamlet"}}, {"type": "node", "id": 8220558479, "lat": 16.3889906, "lon": 121.1346853, "tags": {"admin_level": "10", "designation": "barangay", "name": "San Fernando", "place": "village"}}, {"type": "node", "id": 8220558480, "lat": 16.3801179, "lon": 121.1363268, "tags": {"place": "village"}}, {"type": "node", "id": 8220558482, "lat": 16.416872, "lon": 121.1240637, "tags": {"place": "village"}}, {"type": "node", "id": 8220558483, "lat": 16.4141859, "lon": 121.1331081, "tags": {"admin_level": "10", "name": "Abinganan", "place": "village", "place:PH": "barangay"}}, {"type": "node", "id": 8220558634, "lat": 16.4134089, "lon": 121.0357386, "tags": {"place": "hamlet"}}, {"type": "node", "id": 8220558643, "lat": 16.402551, "lon": 121.0798287, "tags": {"place": "hamlet"}}, {"type": "node", "id": 8220558682, "lat": 16.3952279, "lon": 121.0614449, "tags": {"admin_level": "10", "designation": "barangay", "name": "Manamtam", "place": "village"}}, {"type": "node", "id": 8220558683, "lat": 16.3877554, "lon": 121.070441, "tags": {"place": "hamlet"}}, {"type": "node", "id": 8220558684, "lat": 16.3686816, "lon": 121.0475993, "tags": {"place": "hamlet"}}, {"type": "node", "id": 8220558818, "lat": 16.3821302, "lon": 120.9816492, "tags": {"place": "hamlet"}}, {"type": "node", "id": 8220559044, "lat": 16.3985318, "lon": 121.0012668, "tags": {"place": "hamlet"}}, {"type": "node", "id": 8220559045, "lat": 16.3918159, "lon": 121.0037827, "tags": {"name": "Salicpan", "place": "hamlet"}}, {"type": "node", "id": 8220559046, "lat": 16.3839161, "lon": 120.9915197, "tags": {"place": "hamlet"}}, {"type": "node", "id": 8220559047, "lat": 16.3715021, "lon": 120.9887034, "tags": {"admin_level": "10", "designation": "barangay", "name": "Mapayao", "place": "village"}}, {"type": "node", "id": 8220559093, "lat": 16.3646412, "lon": 120.9676695, "tags": {"admin_level": "10", "designation": "barangay", "name": "Acacia", "place": "village"}}, {"type": "node", "id": 8220559094, "lat": 16.3945332, "lon": 120.9766066, "tags": {"name": "Oliweg", "place": "hamlet"}}, {"type": "node", "id": 8220559332, "lat": 16.4061558, "lon": 120.960516, "tags": {"place": "hamlet"}}, {"type": "node", "id": 8220559399, "lat": 16.4000963, "lon": 120.9531105, "tags": {"place": "hamlet"}}, {"type": "node", "id": 8220559471, "lat": 16.3897008, "lon": 120.9656739, "tags": {"place": "hamlet"}}, {"type": "node", "id": 8220559490, "lat": 16.3919137, "lon": 120.8683419, "tags": {"admin_level": "11", "admin_type:PH": "sitio", "is_in:town": "Bokod", "is_in:village": "Pito", "name": "Pilpiloy", "place": "hamlet"}}, {"type": "node", "id": 8220559491, "lat": 16.4099972, "lon": 120.910694, "tags": {"place": "hamlet"}}, {"type": "node", "id": 8220559595, "lat": 16.3663474, "lon": 120.9303331, "tags": {"place": "hamlet"}}, {"type": "node", "id": 8220559636, "lat": 16.3760133, "lon": 120.928461, "tags": {"place": "hamlet"}}, {"type": "node", "id": 8220559703, "lat": 16.3905962, "lon": 120.9448171, "tags": {"admin_level": "10", "admin_type:PH": "barangay", "name": "Binalian", "place": "village"}}, {"type": "node", "id": 8220559764, "lat": 16.3723102, "lon": 120.88447, "tags": {"admin_level": "10", "admin_type:PH": "barangay", "name": "Balangabang", "place": "village"}}, {"type": "node", "id": 8220560218, "lat": 16.3929867, "lon": 120.8902153, "tags": {"place": "hamlet"}}, {"type": "node", "id": 8220560367, "lat": 16.4102031, "lon": 120.8828151, "tags": {"place": "hamlet"}}, {"type": "node", "id": 8225351890, "lat": 16.3962057, "lon": 121.182273, "tags": {"place": "hamlet"}}, {"type": "node", "id": 8225351891, "lat": 16.3954338, "lon": 121.1945254, "tags": {"place": "hamlet"}}, {"type": "node", "id": 8225351892, "lat": 16.4013622, "lon": 121.171807, "tags": {"admin_level": "10", "designation": "barangay", "name": "Mabuslo", "place": "village"}}, {"type": "node", "id": 8225353152, "lat": 16.39741, "lon": 121.0337376, "tags": {"admin_level": "10", "designation": "barangay", "name": "Pallas", "place": "village"}}, {"type": "node", "id": 8235748963, "lat": 16.4160847, "lon": 121.2771213, "tags": {"place": "hamlet"}}, {"type": "node", "id": 8745519518, "lat": 16.1758114, "lon": 120.8725637, "tags": {"admin_level": "10", "is_in:province": "Pangasinan", "is_in:town": "San Nicolas", "name": "Malico", "note": "ongoing boundary dispute", "place": "village", "place:PH": "barangay"}}, {"type": "node", "id": 9061350104, "lat": 16.3139066, "lon": 120.9728858, "tags": {"name": "Purok 1", "place": "neighbourhood"}}, {"type": "node", "id": 9061374739, "lat": 16.2015316, "lon": 120.9562369, "tags": {"admin_level": "10", "admin_type:PH": "barangay", "name": "Balete", "place": "village"}}, {"type": "node", "id": 9404660716, "lat": 16.3771328, "lon": 121.1336016, "tags": {"admin_level": "10", "designation": "barangay", "name": "Dullao", "place": "village"}}, {"type": "node", "id": 9404739988, "lat": 16.3791451, "lon": 121.1720055, "tags": {"admin_level": "11", "designation": "sitio", "name": "Labni", "place": "hamlet"}}, {"type": "node", "id": 9404770729, "lat": 16.3778224, "lon": 121.0828435, "tags": {"admin_level": "10", "designation": "barangay", "name": "Aliaga", "place": "village"}}, {"type": "node", "id": 9404778355, "lat": 16.3597874, "lon": 121.0217643, "tags": {"admin_level": "11", "designation": "sitio", "name": "Nangcalapan", "place": "hamlet"}}, {"type": "node", "id": 9404781423, "lat": 16.3784606, "lon": 121.1113822, "tags": {"admin_level": "10", "designation": "barangay", "name": "Magsaysay Hill", "place": "village"}}, {"type": "node", "id": 9419696898, "lat": 15.9967432, "lon": 121.1654717, "tags": {"admin_level": "11", "admin_type:PH": "sitio", "is_in:town": "Carranglan", "is_in:village": "San Agustin", "name": "Binbin", "place": "hamlet", "source:name": "extrapolated from OSMaPaaralan, way/1021323855"}}, {"type": "node", "id": 9422191985, "lat": 16.2011372, "lon": 121.2010968, "tags": {"admin_level": "10", "designation": "barangay", "name": "Kinabuan", "place": "village"}}, {"type": "node", "id": 9422576568, "lat": 16.3654698, "lon": 121.1869615, "tags": {"admin_level": "10", "designation": "barangay", "name": "Nantawakan", "place": "village"}}, {"type": "node", "id": 9427102742, "lat": 16.3548563, "lon": 120.9295607, "tags": {"admin_level": "10", "designation": "barangay", "name": "Cabanglasan", "place": "village"}}, {"type": "node", "id": 9427142439, "lat": 16.3147878, "lon": 120.9700003, "tags": {"admin_level": "10", "admin_type:PH": "barangay", "is_in:town": "Kayapa", "name": "Baan", "place": "village"}}, {"type": "node", "id": 9441383446, "lat": 16.1293596, "lon": 121.2970923, "tags": {"admin_level": "10", "admin_type:PH": "barangay", "name": "Guino", "old_name": "Giayan", "place": "village", "population": "1766", "ref": "025706004", "source": "Philippine Census 2020, PSA"}}, {"type": "node", "id": 10743068452, "lat": 16.1581326, "lon": 120.9357894, "tags": {"admin_level": "10", "designation": "barangay", "is_in:town": "Santa Fe", "name": "Poblacion", "place": "village"}}, {"type": "node", "id": 11346716262, "lat": 16.3492456, "lon": 121.1077398, "tags": {"admin_level": "10", "admin_type:PH": "barangay", "name": "San Antonio South", "place": "village"}}, {"type": "node", "id": 11346854395, "lat": 16.3665044, "lon": 121.1044782, "tags": {"admin_level": "10", "admin_type:PH": "barangay", "name": "San Antonio North", "place": "village"}}, {"type": "node", "id": 11346854399, "lat": 16.3653154, "lon": 121.0998917, "tags": {"name": "Bernabe's Subdivision", "place": "neighbourhood"}}, {"type": "node", "id": 11351058396, "lat": 16.0823337, "lon": 120.9409359, "tags": {"admin_level": "11", "name": "Fori", "place": "hamlet"}}, {"type": "node", "id": 12657055953, "lat": 16.3884605, "lon": 121.1113661, "tags": {"admin_level": "11", "admin_type:PH": "purok", "is_in:town": "Bambang", "is_in:village": "Banggot", "name": "Purok 8", "place": "hamlet"}}, {"type": "node", "id": 12732868790, "lat": 16.0000847, "lon": 121.0436511, "tags": {"admin_level": "10", "admin_type:PH": "barangay", "name": "Bunga", "place": "village"}}, {"type": "node", "id": 12749613917, "lat": 16.3617999, "lon": 120.8815008, "tags": {"admin_level": "10", "admin_type:PH": "barangay", "name": "Tubongan", "place": "village"}}, {"type": "node", "id": 12749722457, "lat": 16.2628412, "lon": 121.0291511, "tags": {"admin_level": "11", "admin_type:PH": "sitio", "is_in:town": "Aritao", "is_in:village": "Comon", "name": "Gasajas", "place": "hamlet"}}, {"type": "node", "id": 12749768995, "lat": 16.2411697, "lon": 120.953089, "tags": {"admin_level": "10", "admin_type:PH": "barangay", "is_in:town": "Santa Fe", "name": "Buyasyas", "place": "village"}}, {"type": "node", "id": 12749768996, "lat": 16.2580879, "lon": 120.9552669, "tags": {"admin_level": "10", "admin_type:PH": "barangay", "is_in:town": "Kayapa", "name": "Buyasyas", "place": "village"}}, {"type": "way", "id": 368241660, "nodes": [3719880982, 3720930912, 3720930913, 3720933157, 3720933171, 3720933186, 3720933212, 3720933217, 3720933200, 3720933174, 3720933127, 3719880982], "tags": {"is_in:province": "Nueva Vizcaya", "is_in:town": "Dupax Del Norte", "is_in:village": "Macabenga", "name": "Gawad Kalinga Village - Macabenga", "place": "neighbourhood"}}]}